{
  "version": "1.0.0",
  "producer": ".NET AppCAT CLI",
  "metadata": {
    "analysisStartTime": "2026-03-05T06:53:50.044026Z",
    "analysisEndTime": "2026-03-05T06:53:52.3098707Z",
    "privacyMode": "Restricted",
    "privacyModeHelpUrl": "https://go.microsoft.com/fwlink/?linkid=2271074",
    "targetIds": [
      "AppService.Windows",
      "AppService.Linux",
      "AKS.Linux",
      "AKS.Windows",
      "ACA",
      "AppServiceContainer.Linux",
      "AppServiceContainer.Windows",
      "AppServiceManagedInstance.Windows"
    ],
    "targetDisplayNames": [
      "Azure App Service",
      "Azure Kubernetes Service",
      "Azure Container Apps",
      "Azure App Service Container",
      "Azure App Service Managed Instance"
    ],
    "os": [
      "windows",
      "linux"
    ]
  },
  "summary": {
    "totalProjects": 2,
    "totalIssues": 8,
    "totalIncidents": 54,
    "totalEffort": 70,
    "charts": {
      "severity": {
        "mandatory": 0,
        "optional": 6,
        "potential": 48,
        "information": 0
      },
      "category": {
        "Runtime": 2,
        "Database": 2,
        "Security": 2,
        "Scale": 1,
        "Local": 47
      }
    }
  },
  "projects": [
    {
      "path": "src\\eShopWCFService\\eShopWCFService.csproj",
      "issues": 4,
      "storyPoints": 15,
      "properties": {
        "appName": "eShopWCFService",
        "frameworks": [
          ".NETFramework,Version=v4.6.1"
        ],
        "languages": [
          "C#"
        ],
        "tools": [
          "MSBuild"
        ]
      },
      "incidents": [
        {
          "ruleId": "Runtime.0002",
          "incidentId": "2888508f-29a9-4337-8cc7-14e42b5dd0b9",
          "location": "src\\eShopWCFService\\eShopWCFService.csproj",
          "locationKind": "File",
          "targets": {
            "AppService.Windows": {
              "severity": "optional",
              "effort": 3
            },
            "AppService.Linux": {
              "severity": "mandatory",
              "effort": 3
            },
            "AKS.Linux": {
              "severity": "mandatory",
              "effort": 3
            },
            "AKS.Windows": {
              "severity": "information",
              "effort": 3
            },
            "ACA": {
              "severity": "mandatory",
              "effort": 3
            },
            "AppServiceContainer.Linux": {
              "severity": "mandatory",
              "effort": 3
            },
            "AppServiceContainer.Windows": {
              "severity": "information",
              "effort": 3
            },
            "AppServiceManagedInstance.Windows": {
              "severity": "optional",
              "effort": 3
            }
          },
          "labels": []
        },
        {
          "ruleId": "Database.0002",
          "incidentId": "8c3bf657-2d21-405e-ad12-e0f7fbb431f9",
          "location": "src\\eShopWCFService\\Web.config",
          "locationKind": "File",
          "targets": {
            "AppService.Windows": {
              "severity": "potential",
              "effort": 3
            },
            "AppService.Linux": {
              "severity": "potential",
              "effort": 3
            },
            "AKS.Linux": {
              "severity": "potential",
              "effort": 3
            },
            "AKS.Windows": {
              "severity": "potential",
              "effort": 3
            },
            "ACA": {
              "severity": "potential",
              "effort": 3
            },
            "AppServiceContainer.Linux": {
              "severity": "potential",
              "effort": 3
            },
            "AppServiceContainer.Windows": {
              "severity": "potential",
              "effort": 3
            },
            "AppServiceManagedInstance.Windows": {
              "severity": "potential",
              "effort": 3
            }
          },
          "labels": []
        },
        {
          "ruleId": "Database.0003",
          "incidentId": "201db4e4-5c65-4206-90a2-a0f03c17b5e7",
          "location": "src\\eShopWCFService\\Web.config",
          "locationKind": "File",
          "targets": {
            "AppService.Windows": {
              "severity": "optional",
              "effort": 3
            },
            "AppService.Linux": {
              "severity": "optional",
              "effort": 3
            },
            "AKS.Linux": {
              "severity": "optional",
              "effort": 3
            },
            "AKS.Windows": {
              "severity": "optional",
              "effort": 3
            },
            "ACA": {
              "severity": "optional",
              "effort": 3
            },
            "AppServiceContainer.Linux": {
              "severity": "optional",
              "effort": 3
            },
            "AppServiceContainer.Windows": {
              "severity": "optional",
              "effort": 3
            },
            "AppServiceManagedInstance.Windows": {
              "severity": "optional",
              "effort": 3
            }
          },
          "labels": []
        },
        {
          "ruleId": "Security.0002",
          "incidentId": "98224e9a-7e12-484c-99e6-e3a92513296d",
          "location": "src\\eShopWCFService\\Web.config",
          "locationKind": "File",
          "targets": {
            "AppService.Windows": {
              "severity": "optional",
              "effort": 3
            },
            "AppService.Linux": {
              "severity": "optional",
              "effort": 3
            },
            "AKS.Linux": {
              "severity": "optional",
              "effort": 3
            },
            "AKS.Windows": {
              "severity": "optional",
              "effort": 3
            },
            "ACA": {
              "severity": "optional",
              "effort": 3
            },
            "AppServiceContainer.Linux": {
              "severity": "optional",
              "effort": 3
            },
            "AppServiceContainer.Windows": {
              "severity": "optional",
              "effort": 3
            },
            "AppServiceManagedInstance.Windows": {
              "severity": "optional",
              "effort": 3
            }
          },
          "labels": []
        },
        {
          "ruleId": "Security.0002",
          "incidentId": "d582f007-85a5-4428-a77b-d7a8cff148e2",
          "location": "src\\eShopWCFService\\Web.config",
          "locationKind": "File",
          "targets": {
            "AppService.Windows": {
              "severity": "optional",
              "effort": 3
            },
            "AppService.Linux": {
              "severity": "optional",
              "effort": 3
            },
            "AKS.Linux": {
              "severity": "optional",
              "effort": 3
            },
            "AKS.Windows": {
              "severity": "optional",
              "effort": 3
            },
            "ACA": {
              "severity": "optional",
              "effort": 3
            },
            "AppServiceContainer.Linux": {
              "severity": "optional",
              "effort": 3
            },
            "AppServiceContainer.Windows": {
              "severity": "optional",
              "effort": 3
            },
            "AppServiceManagedInstance.Windows": {
              "severity": "optional",
              "effort": 3
            }
          },
          "labels": []
        }
      ]
    },
    {
      "path": "src\\eShopWinForms\\eShopWinForms.csproj",
      "issues": 5,
      "storyPoints": 55,
      "properties": {
        "appName": "eShopWinForms",
        "frameworks": [
          ".NETFramework,Version=v4.7"
        ],
        "languages": [
          "C#"
        ],
        "tools": [
          "MSBuild"
        ]
      },
      "incidents": [
        {
          "ruleId": "Runtime.0002",
          "incidentId": "66f2d813-2464-48c9-83d8-000346f742d8",
          "location": "src\\eShopWinForms\\eShopWinForms.csproj",
          "locationKind": "File",
          "targets": {
            "AppService.Windows": {
              "severity": "optional",
              "effort": 3
            },
            "AppService.Linux": {
              "severity": "mandatory",
              "effort": 3
            },
            "AKS.Linux": {
              "severity": "mandatory",
              "effort": 3
            },
            "AKS.Windows": {
              "severity": "information",
              "effort": 3
            },
            "ACA": {
              "severity": "mandatory",
              "effort": 3
            },
            "AppServiceContainer.Linux": {
              "severity": "mandatory",
              "effort": 3
            },
            "AppServiceContainer.Windows": {
              "severity": "information",
              "effort": 3
            },
            "AppServiceManagedInstance.Windows": {
              "severity": "optional",
              "effort": 3
            }
          },
          "labels": []
        },
        {
          "ruleId": "Scale.0001",
          "incidentId": "246e44e0-e418-42b4-8c2e-90198804d47b",
          "location": "src\\eShopWinForms\\eShopWinForms.csproj",
          "locationKind": "File",
          "targets": {
            "AppService.Windows": {
              "severity": "optional",
              "effort": 3
            },
            "AppService.Linux": {
              "severity": "optional",
              "effort": 3
            },
            "AKS.Linux": {
              "severity": "optional",
              "effort": 3
            },
            "AKS.Windows": {
              "severity": "optional",
              "effort": 3
            },
            "ACA": {
              "severity": "optional",
              "effort": 3
            },
            "AppServiceContainer.Linux": {
              "severity": "optional",
              "effort": 3
            },
            "AppServiceContainer.Windows": {
              "severity": "optional",
              "effort": 3
            },
            "AppServiceManagedInstance.Windows": {
              "severity": "optional",
              "effort": 3
            }
          },
          "labels": []
        },
        {
          "ruleId": "Local.0003",
          "incidentId": "a1f89cab-441d-47ee-8828-81e259a5e9c0",
          "location": "src\\eShopWinForms\\Views\\CatalogView.cs",
          "locationKind": "File",
          "line": 57,
          "column": 28,
          "targets": {
            "AppService.Windows": {
              "severity": "potential",
              "effort": 3
            },
            "AppService.Linux": {
              "severity": "potential",
              "effort": 3
            },
            "AKS.Linux": {
              "severity": "potential",
              "effort": 3
            },
            "AKS.Windows": {
              "severity": "potential",
              "effort": 3
            },
            "ACA": {
              "severity": "potential",
              "effort": 3
            },
            "AppServiceContainer.Linux": {
              "severity": "potential",
              "effort": 3
            },
            "AppServiceContainer.Windows": {
              "severity": "potential",
              "effort": 3
            },
            "AppServiceManagedInstance.Windows": {
              "severity": "potential",
              "effort": 3
            }
          },
          "labels": []
        },
        {
          "ruleId": "Local.0007",
          "incidentId": "f2e75b56-bce8-4a95-b882-6cfb3e985176",
          "location": "src\\eShopWinForms\\Views\\CatalogView.cs",
          "locationKind": "File",
          "line": 56,
          "column": 35,
          "targets": {
            "AppService.Windows": {
              "severity": "potential",
              "effort": 1
            },
            "AppService.Linux": {
              "severity": "potential",
              "effort": 1
            },
            "AKS.Linux": {
              "severity": "potential",
              "effort": 1
            },
            "AKS.Windows": {
              "severity": "potential",
              "effort": 1
            },
            "ACA": {
              "severity": "potential",
              "effort": 1
            },
            "AppServiceContainer.Linux": {
              "severity": "potential",
              "effort": 1
            },
            "AppServiceContainer.Windows": {
              "severity": "potential",
              "effort": 1
            },
            "AppServiceManagedInstance.Windows": {
              "severity": "information",
              "effort": 1
            }
          },
          "labels": []
        },
        {
          "ruleId": "Local.0006",
          "incidentId": "31b27a0c-dc72-4b9b-9bad-2232a72d04ce",
          "location": "src\\eShopWinForms\\Connected Services\\eShopServiceReference\\Reference.cs",
          "locationKind": "File",
          "line": 17,
          "column": 86,
          "targets": {
            "AppService.Windows": {
              "severity": "potential",
              "effort": 1
            },
            "AppService.Linux": {
              "severity": "potential",
              "effort": 1
            },
            "AKS.Linux": {
              "severity": "potential",
              "effort": 1
            },
            "AKS.Windows": {
              "severity": "potential",
              "effort": 1
            },
            "ACA": {
              "severity": "potential",
              "effort": 1
            },
            "AppServiceContainer.Linux": {
              "severity": "potential",
              "effort": 1
            },
            "AppServiceContainer.Windows": {
              "severity": "potential",
              "effort": 1
            },
            "AppServiceManagedInstance.Windows": {
              "severity": "potential",
              "effort": 1
            }
          },
          "labels": []
        },
        {
          "ruleId": "Local.0006",
          "incidentId": "c137401b-d7d8-469e-873d-bf6d761110a9",
          "location": "src\\eShopWinForms\\Connected Services\\eShopServiceReference\\Reference.cs",
          "locationKind": "File",
          "line": 190,
          "column": 87,
          "targets": {
            "AppService.Windows": {
              "severity": "potential",
              "effort": 1
            },
            "AppService.Linux": {
              "severity": "potential",
              "effort": 1
            },
            "AKS.Linux": {
              "severity": "potential",
              "effort": 1
            },
            "AKS.Windows": {
              "severity": "potential",
              "effort": 1
            },
            "ACA": {
              "severity": "potential",
              "effort": 1
            },
            "AppServiceContainer.Linux": {
              "severity": "potential",
              "effort": 1
            },
            "AppServiceContainer.Windows": {
              "severity": "potential",
              "effort": 1
            },
            "AppServiceManagedInstance.Windows": {
              "severity": "potential",
              "effort": 1
            }
          },
          "labels": []
        },
        {
          "ruleId": "Local.0006",
          "incidentId": "c1a124ac-5be1-4f48-9b3c-c131942b37a0",
          "location": "src\\eShopWinForms\\Connected Services\\eShopServiceReference\\Reference.cs",
          "locationKind": "File",
          "line": 251,
          "column": 86,
          "targets": {
            "AppService.Windows": {
              "severity": "potential",
              "effort": 1
            },
            "AppService.Linux": {
              "severity": "potential",
              "effort": 1
            },
            "AKS.Linux": {
              "severity": "potential",
              "effort": 1
            },
            "AKS.Windows": {
              "severity": "potential",
              "effort": 1
            },
            "ACA": {
              "severity": "potential",
              "effort": 1
            },
            "AppServiceContainer.Linux": {
              "severity": "potential",
              "effort": 1
            },
            "AppServiceContainer.Windows": {
              "severity": "potential",
              "effort": 1
            },
            "AppServiceManagedInstance.Windows": {
              "severity": "potential",
              "effort": 1
            }
          },
          "labels": []
        },
        {
          "ruleId": "Local.0006",
          "incidentId": "dc26164f-f34f-4789-bbc6-f23234401288",
          "location": "src\\eShopWinForms\\Connected Services\\eShopServiceReference\\Reference.cs",
          "locationKind": "File",
          "line": 405,
          "column": 87,
          "targets": {
            "AppService.Windows": {
              "severity": "potential",
              "effort": 1
            },
            "AppService.Linux": {
              "severity": "potential",
              "effort": 1
            },
            "AKS.Linux": {
              "severity": "potential",
              "effort": 1
            },
            "AKS.Windows": {
              "severity": "potential",
              "effort": 1
            },
            "ACA": {
              "severity": "potential",
              "effort": 1
            },
            "AppServiceContainer.Linux": {
              "severity": "potential",
              "effort": 1
            },
            "AppServiceContainer.Windows": {
              "severity": "potential",
              "effort": 1
            },
            "AppServiceManagedInstance.Windows": {
              "severity": "potential",
              "effort": 1
            }
          },
          "labels": []
        },
        {
          "ruleId": "Local.0006",
          "incidentId": "43da57e7-8b42-486f-a808-dadb7f15b970",
          "location": "src\\eShopWinForms\\Connected Services\\eShopServiceReference\\Reference.cs",
          "locationKind": "File",
          "line": 312,
          "column": 92,
          "targets": {
            "AppService.Windows": {
              "severity": "potential",
              "effort": 1
            },
            "AppService.Linux": {
              "severity": "potential",
              "effort": 1
            },
            "AKS.Linux": {
              "severity": "potential",
              "effort": 1
            },
            "AKS.Windows": {
              "severity": "potential",
              "effort": 1
            },
            "ACA": {
              "severity": "potential",
              "effort": 1
            },
            "AppServiceContainer.Linux": {
              "severity": "potential",
              "effort": 1
            },
            "AppServiceContainer.Windows": {
              "severity": "potential",
              "effort": 1
            },
            "AppServiceManagedInstance.Windows": {
              "severity": "potential",
              "effort": 1
            }
          },
          "labels": []
        },
        {
          "ruleId": "Local.0006",
          "incidentId": "3f6defc7-e355-44be-9652-518348a51019",
          "location": "src\\eShopWinForms\\Connected Services\\eShopServiceReference\\Reference.cs",
          "locationKind": "File",
          "line": 530,
          "column": 63,
          "targets": {
            "AppService.Windows": {
              "severity": "potential",
              "effort": 1
            },
            "AppService.Linux": {
              "severity": "potential",
              "effort": 1
            },
            "AKS.Linux": {
              "severity": "potential",
              "effort": 1
            },
            "AKS.Windows": {
              "severity": "potential",
              "effort": 1
            },
            "ACA": {
              "severity": "potential",
              "effort": 1
            },
            "AppServiceContainer.Linux": {
              "severity": "potential",
              "effort": 1
            },
            "AppServiceContainer.Windows": {
              "severity": "potential",
              "effort": 1
            },
            "AppServiceManagedInstance.Windows": {
              "severity": "potential",
              "effort": 1
            }
          },
          "labels": []
        },
        {
          "ruleId": "Local.0006",
          "incidentId": "4a3858fd-5894-430a-9910-8869ec325777",
          "location": "src\\eShopWinForms\\Connected Services\\eShopServiceReference\\Reference.cs",
          "locationKind": "File",
          "line": 533,
          "column": 63,
          "targets": {
            "AppService.Windows": {
              "severity": "potential",
              "effort": 1
            },
            "AppService.Linux": {
              "severity": "potential",
              "effort": 1
            },
            "AKS.Linux": {
              "severity": "potential",
              "effort": 1
            },
            "AKS.Windows": {
              "severity": "potential",
              "effort": 1
            },
            "ACA": {
              "severity": "potential",
              "effort": 1
            },
            "AppServiceContainer.Linux": {
              "severity": "potential",
              "effort": 1
            },
            "AppServiceContainer.Windows": {
              "severity": "potential",
              "effort": 1
            },
            "AppServiceManagedInstance.Windows": {
              "severity": "potential",
              "effort": 1
            }
          },
          "labels": []
        },
        {
          "ruleId": "Local.0006",
          "incidentId": "c1670157-4b81-41a7-82ec-0d34432ff72a",
          "location": "src\\eShopWinForms\\Connected Services\\eShopServiceReference\\Reference.cs",
          "locationKind": "File",
          "line": 530,
          "column": 134,
          "targets": {
            "AppService.Windows": {
              "severity": "potential",
              "effort": 1
            },
            "AppService.Linux": {
              "severity": "potential",
              "effort": 1
            },
            "AKS.Linux": {
              "severity": "potential",
              "effort": 1
            },
            "AKS.Windows": {
              "severity": "potential",
              "effort": 1
            },
            "ACA": {
              "severity": "potential",
              "effort": 1
            },
            "AppServiceContainer.Linux": {
              "severity": "potential",
              "effort": 1
            },
            "AppServiceContainer.Windows": {
              "severity": "potential",
              "effort": 1
            },
            "AppServiceManagedInstance.Windows": {
              "severity": "potential",
              "effort": 1
            }
          },
          "labels": []
        },
        {
          "ruleId": "Local.0006",
          "incidentId": "5526e621-8e49-4c67-baa8-9cd70e0ee7ce",
          "location": "src\\eShopWinForms\\Connected Services\\eShopServiceReference\\Reference.cs",
          "locationKind": "File",
          "line": 533,
          "column": 134,
          "targets": {
            "AppService.Windows": {
              "severity": "potential",
              "effort": 1
            },
            "AppService.Linux": {
              "severity": "potential",
              "effort": 1
            },
            "AKS.Linux": {
              "severity": "potential",
              "effort": 1
            },
            "AKS.Windows": {
              "severity": "potential",
              "effort": 1
            },
            "ACA": {
              "severity": "potential",
              "effort": 1
            },
            "AppServiceContainer.Linux": {
              "severity": "potential",
              "effort": 1
            },
            "AppServiceContainer.Windows": {
              "severity": "potential",
              "effort": 1
            },
            "AppServiceManagedInstance.Windows": {
              "severity": "potential",
              "effort": 1
            }
          },
          "labels": []
        },
        {
          "ruleId": "Local.0006",
          "incidentId": "302cdf8d-157a-4b22-af71-d8f60b42edcb",
          "location": "src\\eShopWinForms\\Connected Services\\eShopServiceReference\\Reference.cs",
          "locationKind": "File",
          "line": 536,
          "column": 63,
          "targets": {
            "AppService.Windows": {
              "severity": "potential",
              "effort": 1
            },
            "AppService.Linux": {
              "severity": "potential",
              "effort": 1
            },
            "AKS.Linux": {
              "severity": "potential",
              "effort": 1
            },
            "AKS.Windows": {
              "severity": "potential",
              "effort": 1
            },
            "ACA": {
              "severity": "potential",
              "effort": 1
            },
            "AppServiceContainer.Linux": {
              "severity": "potential",
              "effort": 1
            },
            "AppServiceContainer.Windows": {
              "severity": "potential",
              "effort": 1
            },
            "AppServiceManagedInstance.Windows": {
              "severity": "potential",
              "effort": 1
            }
          },
          "labels": []
        },
        {
          "ruleId": "Local.0006",
          "incidentId": "eaa7e9a9-124c-45ae-9850-d1517ad05cd0",
          "location": "src\\eShopWinForms\\Connected Services\\eShopServiceReference\\Reference.cs",
          "locationKind": "File",
          "line": 539,
          "column": 63,
          "targets": {
            "AppService.Windows": {
              "severity": "potential",
              "effort": 1
            },
            "AppService.Linux": {
              "severity": "potential",
              "effort": 1
            },
            "AKS.Linux": {
              "severity": "potential",
              "effort": 1
            },
            "AKS.Windows": {
              "severity": "potential",
              "effort": 1
            },
            "ACA": {
              "severity": "potential",
              "effort": 1
            },
            "AppServiceContainer.Linux": {
              "severity": "potential",
              "effort": 1
            },
            "AppServiceContainer.Windows": {
              "severity": "potential",
              "effort": 1
            },
            "AppServiceManagedInstance.Windows": {
              "severity": "potential",
              "effort": 1
            }
          },
          "labels": []
        },
        {
          "ruleId": "Local.0006",
          "incidentId": "ed860369-eeac-451d-a089-6fe7797fc2bc",
          "location": "src\\eShopWinForms\\Connected Services\\eShopServiceReference\\Reference.cs",
          "locationKind": "File",
          "line": 536,
          "column": 131,
          "targets": {
            "AppService.Windows": {
              "severity": "potential",
              "effort": 1
            },
            "AppService.Linux": {
              "severity": "potential",
              "effort": 1
            },
            "AKS.Linux": {
              "severity": "potential",
              "effort": 1
            },
            "AKS.Windows": {
              "severity": "potential",
              "effort": 1
            },
            "ACA": {
              "severity": "potential",
              "effort": 1
            },
            "AppServiceContainer.Linux": {
              "severity": "potential",
              "effort": 1
            },
            "AppServiceContainer.Windows": {
              "severity": "potential",
              "effort": 1
            },
            "AppServiceManagedInstance.Windows": {
              "severity": "potential",
              "effort": 1
            }
          },
          "labels": []
        },
        {
          "ruleId": "Local.0006",
          "incidentId": "bba44a24-0cc8-4c5c-bb22-69c03ebede5b",
          "location": "src\\eShopWinForms\\Connected Services\\eShopServiceReference\\Reference.cs",
          "locationKind": "File",
          "line": 539,
          "column": 131,
          "targets": {
            "AppService.Windows": {
              "severity": "potential",
              "effort": 1
            },
            "AppService.Linux": {
              "severity": "potential",
              "effort": 1
            },
            "AKS.Linux": {
              "severity": "potential",
              "effort": 1
            },
            "AKS.Windows": {
              "severity": "potential",
              "effort": 1
            },
            "ACA": {
              "severity": "potential",
              "effort": 1
            },
            "AppServiceContainer.Linux": {
              "severity": "potential",
              "effort": 1
            },
            "AppServiceContainer.Windows": {
              "severity": "potential",
              "effort": 1
            },
            "AppServiceManagedInstance.Windows": {
              "severity": "potential",
              "effort": 1
            }
          },
          "labels": []
        },
        {
          "ruleId": "Local.0006",
          "incidentId": "81bbaf7a-745f-4c98-927f-e04f051de0c3",
          "location": "src\\eShopWinForms\\Connected Services\\eShopServiceReference\\Reference.cs",
          "locationKind": "File",
          "line": 500,
          "column": 63,
          "targets": {
            "AppService.Windows": {
              "severity": "potential",
              "effort": 1
            },
            "AppService.Linux": {
              "severity": "potential",
              "effort": 1
            },
            "AKS.Linux": {
              "severity": "potential",
              "effort": 1
            },
            "AKS.Windows": {
              "severity": "potential",
              "effort": 1
            },
            "ACA": {
              "severity": "potential",
              "effort": 1
            },
            "AppServiceContainer.Linux": {
              "severity": "potential",
              "effort": 1
            },
            "AppServiceContainer.Windows": {
              "severity": "potential",
              "effort": 1
            },
            "AppServiceManagedInstance.Windows": {
              "severity": "potential",
              "effort": 1
            }
          },
          "labels": []
        },
        {
          "ruleId": "Local.0006",
          "incidentId": "fd492d27-5ef8-4a7e-8c3d-ccb1bba14757",
          "location": "src\\eShopWinForms\\Connected Services\\eShopServiceReference\\Reference.cs",
          "locationKind": "File",
          "line": 503,
          "column": 63,
          "targets": {
            "AppService.Windows": {
              "severity": "potential",
              "effort": 1
            },
            "AppService.Linux": {
              "severity": "potential",
              "effort": 1
            },
            "AKS.Linux": {
              "severity": "potential",
              "effort": 1
            },
            "AKS.Windows": {
              "severity": "potential",
              "effort": 1
            },
            "ACA": {
              "severity": "potential",
              "effort": 1
            },
            "AppServiceContainer.Linux": {
              "severity": "potential",
              "effort": 1
            },
            "AppServiceContainer.Windows": {
              "severity": "potential",
              "effort": 1
            },
            "AppServiceManagedInstance.Windows": {
              "severity": "potential",
              "effort": 1
            }
          },
          "labels": []
        },
        {
          "ruleId": "Local.0006",
          "incidentId": "b5b99080-caa5-4a2e-b79f-254ad7d1c151",
          "location": "src\\eShopWinForms\\Connected Services\\eShopServiceReference\\Reference.cs",
          "locationKind": "File",
          "line": 500,
          "column": 129,
          "targets": {
            "AppService.Windows": {
              "severity": "potential",
              "effort": 1
            },
            "AppService.Linux": {
              "severity": "potential",
              "effort": 1
            },
            "AKS.Linux": {
              "severity": "potential",
              "effort": 1
            },
            "AKS.Windows": {
              "severity": "potential",
              "effort": 1
            },
            "ACA": {
              "severity": "potential",
              "effort": 1
            },
            "AppServiceContainer.Linux": {
              "severity": "potential",
              "effort": 1
            },
            "AppServiceContainer.Windows": {
              "severity": "potential",
              "effort": 1
            },
            "AppServiceManagedInstance.Windows": {
              "severity": "potential",
              "effort": 1
            }
          },
          "labels": []
        },
        {
          "ruleId": "Local.0006",
          "incidentId": "6dee7166-9fe8-4846-bf4d-a78a793da67d",
          "location": "src\\eShopWinForms\\Connected Services\\eShopServiceReference\\Reference.cs",
          "locationKind": "File",
          "line": 503,
          "column": 129,
          "targets": {
            "AppService.Windows": {
              "severity": "potential",
              "effort": 1
            },
            "AppService.Linux": {
              "severity": "potential",
              "effort": 1
            },
            "AKS.Linux": {
              "severity": "potential",
              "effort": 1
            },
            "AKS.Windows": {
              "severity": "potential",
              "effort": 1
            },
            "ACA": {
              "severity": "potential",
              "effort": 1
            },
            "AppServiceContainer.Linux": {
              "severity": "potential",
              "effort": 1
            },
            "AppServiceContainer.Windows": {
              "severity": "potential",
              "effort": 1
            },
            "AppServiceManagedInstance.Windows": {
              "severity": "potential",
              "effort": 1
            }
          },
          "labels": []
        },
        {
          "ruleId": "Local.0006",
          "incidentId": "f12e950c-1b71-4228-b26d-6dc9b0b6b996",
          "location": "src\\eShopWinForms\\Connected Services\\eShopServiceReference\\Reference.cs",
          "locationKind": "File",
          "line": 524,
          "column": 63,
          "targets": {
            "AppService.Windows": {
              "severity": "potential",
              "effort": 1
            },
            "AppService.Linux": {
              "severity": "potential",
              "effort": 1
            },
            "AKS.Linux": {
              "severity": "potential",
              "effort": 1
            },
            "AKS.Windows": {
              "severity": "potential",
              "effort": 1
            },
            "ACA": {
              "severity": "potential",
              "effort": 1
            },
            "AppServiceContainer.Linux": {
              "severity": "potential",
              "effort": 1
            },
            "AppServiceContainer.Windows": {
              "severity": "potential",
              "effort": 1
            },
            "AppServiceManagedInstance.Windows": {
              "severity": "potential",
              "effort": 1
            }
          },
          "labels": []
        },
        {
          "ruleId": "Local.0006",
          "incidentId": "407a2ee1-0cce-4099-ad17-ffb39fa91c2e",
          "location": "src\\eShopWinForms\\Connected Services\\eShopServiceReference\\Reference.cs",
          "locationKind": "File",
          "line": 527,
          "column": 63,
          "targets": {
            "AppService.Windows": {
              "severity": "potential",
              "effort": 1
            },
            "AppService.Linux": {
              "severity": "potential",
              "effort": 1
            },
            "AKS.Linux": {
              "severity": "potential",
              "effort": 1
            },
            "AKS.Windows": {
              "severity": "potential",
              "effort": 1
            },
            "ACA": {
              "severity": "potential",
              "effort": 1
            },
            "AppServiceContainer.Linux": {
              "severity": "potential",
              "effort": 1
            },
            "AppServiceContainer.Windows": {
              "severity": "potential",
              "effort": 1
            },
            "AppServiceManagedInstance.Windows": {
              "severity": "potential",
              "effort": 1
            }
          },
          "labels": []
        },
        {
          "ruleId": "Local.0006",
          "incidentId": "c95c5ef2-cd07-48fb-a19c-0772cea7b081",
          "location": "src\\eShopWinForms\\Connected Services\\eShopServiceReference\\Reference.cs",
          "locationKind": "File",
          "line": 524,
          "column": 131,
          "targets": {
            "AppService.Windows": {
              "severity": "potential",
              "effort": 1
            },
            "AppService.Linux": {
              "severity": "potential",
              "effort": 1
            },
            "AKS.Linux": {
              "severity": "potential",
              "effort": 1
            },
            "AKS.Windows": {
              "severity": "potential",
              "effort": 1
            },
            "ACA": {
              "severity": "potential",
              "effort": 1
            },
            "AppServiceContainer.Linux": {
              "severity": "potential",
              "effort": 1
            },
            "AppServiceContainer.Windows": {
              "severity": "potential",
              "effort": 1
            },
            "AppServiceManagedInstance.Windows": {
              "severity": "potential",
              "effort": 1
            }
          },
          "labels": []
        },
        {
          "ruleId": "Local.0006",
          "incidentId": "96862ec9-e60d-4b2e-a8ad-65479ccc2502",
          "location": "src\\eShopWinForms\\Connected Services\\eShopServiceReference\\Reference.cs",
          "locationKind": "File",
          "line": 527,
          "column": 131,
          "targets": {
            "AppService.Windows": {
              "severity": "potential",
              "effort": 1
            },
            "AppService.Linux": {
              "severity": "potential",
              "effort": 1
            },
            "AKS.Linux": {
              "severity": "potential",
              "effort": 1
            },
            "AKS.Windows": {
              "severity": "potential",
              "effort": 1
            },
            "ACA": {
              "severity": "potential",
              "effort": 1
            },
            "AppServiceContainer.Linux": {
              "severity": "potential",
              "effort": 1
            },
            "AppServiceContainer.Windows": {
              "severity": "potential",
              "effort": 1
            },
            "AppServiceManagedInstance.Windows": {
              "severity": "potential",
              "effort": 1
            }
          },
          "labels": []
        },
        {
          "ruleId": "Local.0006",
          "incidentId": "ead56331-4d85-4c76-94bb-dad9e2f6f24d",
          "location": "src\\eShopWinForms\\Connected Services\\eShopServiceReference\\Reference.cs",
          "locationKind": "File",
          "line": 506,
          "column": 63,
          "targets": {
            "AppService.Windows": {
              "severity": "potential",
              "effort": 1
            },
            "AppService.Linux": {
              "severity": "potential",
              "effort": 1
            },
            "AKS.Linux": {
              "severity": "potential",
              "effort": 1
            },
            "AKS.Windows": {
              "severity": "potential",
              "effort": 1
            },
            "ACA": {
              "severity": "potential",
              "effort": 1
            },
            "AppServiceContainer.Linux": {
              "severity": "potential",
              "effort": 1
            },
            "AppServiceContainer.Windows": {
              "severity": "potential",
              "effort": 1
            },
            "AppServiceManagedInstance.Windows": {
              "severity": "potential",
              "effort": 1
            }
          },
          "labels": []
        },
        {
          "ruleId": "Local.0006",
          "incidentId": "750083ad-5c77-4d00-9761-3d9f2636a302",
          "location": "src\\eShopWinForms\\Connected Services\\eShopServiceReference\\Reference.cs",
          "locationKind": "File",
          "line": 509,
          "column": 63,
          "targets": {
            "AppService.Windows": {
              "severity": "potential",
              "effort": 1
            },
            "AppService.Linux": {
              "severity": "potential",
              "effort": 1
            },
            "AKS.Linux": {
              "severity": "potential",
              "effort": 1
            },
            "AKS.Windows": {
              "severity": "potential",
              "effort": 1
            },
            "ACA": {
              "severity": "potential",
              "effort": 1
            },
            "AppServiceContainer.Linux": {
              "severity": "potential",
              "effort": 1
            },
            "AppServiceContainer.Windows": {
              "severity": "potential",
              "effort": 1
            },
            "AppServiceManagedInstance.Windows": {
              "severity": "potential",
              "effort": 1
            }
          },
          "labels": []
        },
        {
          "ruleId": "Local.0006",
          "incidentId": "3ab79d58-818a-4543-ab3f-6df5eeb73b82",
          "location": "src\\eShopWinForms\\Connected Services\\eShopServiceReference\\Reference.cs",
          "locationKind": "File",
          "line": 506,
          "column": 130,
          "targets": {
            "AppService.Windows": {
              "severity": "potential",
              "effort": 1
            },
            "AppService.Linux": {
              "severity": "potential",
              "effort": 1
            },
            "AKS.Linux": {
              "severity": "potential",
              "effort": 1
            },
            "AKS.Windows": {
              "severity": "potential",
              "effort": 1
            },
            "ACA": {
              "severity": "potential",
              "effort": 1
            },
            "AppServiceContainer.Linux": {
              "severity": "potential",
              "effort": 1
            },
            "AppServiceContainer.Windows": {
              "severity": "potential",
              "effort": 1
            },
            "AppServiceManagedInstance.Windows": {
              "severity": "potential",
              "effort": 1
            }
          },
          "labels": []
        },
        {
          "ruleId": "Local.0006",
          "incidentId": "e370f7a0-1f72-4ab1-bc4a-5d56cd8fabaf",
          "location": "src\\eShopWinForms\\Connected Services\\eShopServiceReference\\Reference.cs",
          "locationKind": "File",
          "line": 509,
          "column": 130,
          "targets": {
            "AppService.Windows": {
              "severity": "potential",
              "effort": 1
            },
            "AppService.Linux": {
              "severity": "potential",
              "effort": 1
            },
            "AKS.Linux": {
              "severity": "potential",
              "effort": 1
            },
            "AKS.Windows": {
              "severity": "potential",
              "effort": 1
            },
            "ACA": {
              "severity": "potential",
              "effort": 1
            },
            "AppServiceContainer.Linux": {
              "severity": "potential",
              "effort": 1
            },
            "AppServiceContainer.Windows": {
              "severity": "potential",
              "effort": 1
            },
            "AppServiceManagedInstance.Windows": {
              "severity": "potential",
              "effort": 1
            }
          },
          "labels": []
        },
        {
          "ruleId": "Local.0006",
          "incidentId": "67e5726d-00d2-46e4-a583-aac77d68efad",
          "location": "src\\eShopWinForms\\Connected Services\\eShopServiceReference\\Reference.cs",
          "locationKind": "File",
          "line": 512,
          "column": 63,
          "targets": {
            "AppService.Windows": {
              "severity": "potential",
              "effort": 1
            },
            "AppService.Linux": {
              "severity": "potential",
              "effort": 1
            },
            "AKS.Linux": {
              "severity": "potential",
              "effort": 1
            },
            "AKS.Windows": {
              "severity": "potential",
              "effort": 1
            },
            "ACA": {
              "severity": "potential",
              "effort": 1
            },
            "AppServiceContainer.Linux": {
              "severity": "potential",
              "effort": 1
            },
            "AppServiceContainer.Windows": {
              "severity": "potential",
              "effort": 1
            },
            "AppServiceManagedInstance.Windows": {
              "severity": "potential",
              "effort": 1
            }
          },
          "labels": []
        },
        {
          "ruleId": "Local.0006",
          "incidentId": "ca43f5a6-8ec7-4049-a4b5-2856b846d4fe",
          "location": "src\\eShopWinForms\\Connected Services\\eShopServiceReference\\Reference.cs",
          "locationKind": "File",
          "line": 515,
          "column": 63,
          "targets": {
            "AppService.Windows": {
              "severity": "potential",
              "effort": 1
            },
            "AppService.Linux": {
              "severity": "potential",
              "effort": 1
            },
            "AKS.Linux": {
              "severity": "potential",
              "effort": 1
            },
            "AKS.Windows": {
              "severity": "potential",
              "effort": 1
            },
            "ACA": {
              "severity": "potential",
              "effort": 1
            },
            "AppServiceContainer.Linux": {
              "severity": "potential",
              "effort": 1
            },
            "AppServiceContainer.Windows": {
              "severity": "potential",
              "effort": 1
            },
            "AppServiceManagedInstance.Windows": {
              "severity": "potential",
              "effort": 1
            }
          },
          "labels": []
        },
        {
          "ruleId": "Local.0006",
          "incidentId": "d7d1259a-5600-4cd6-b4e2-bba44966e1f6",
          "location": "src\\eShopWinForms\\Connected Services\\eShopServiceReference\\Reference.cs",
          "locationKind": "File",
          "line": 512,
          "column": 129,
          "targets": {
            "AppService.Windows": {
              "severity": "potential",
              "effort": 1
            },
            "AppService.Linux": {
              "severity": "potential",
              "effort": 1
            },
            "AKS.Linux": {
              "severity": "potential",
              "effort": 1
            },
            "AKS.Windows": {
              "severity": "potential",
              "effort": 1
            },
            "ACA": {
              "severity": "potential",
              "effort": 1
            },
            "AppServiceContainer.Linux": {
              "severity": "potential",
              "effort": 1
            },
            "AppServiceContainer.Windows": {
              "severity": "potential",
              "effort": 1
            },
            "AppServiceManagedInstance.Windows": {
              "severity": "potential",
              "effort": 1
            }
          },
          "labels": []
        },
        {
          "ruleId": "Local.0006",
          "incidentId": "caedf622-a20e-4951-80d7-fe1f1791f9e8",
          "location": "src\\eShopWinForms\\Connected Services\\eShopServiceReference\\Reference.cs",
          "locationKind": "File",
          "line": 515,
          "column": 129,
          "targets": {
            "AppService.Windows": {
              "severity": "potential",
              "effort": 1
            },
            "AppService.Linux": {
              "severity": "potential",
              "effort": 1
            },
            "AKS.Linux": {
              "severity": "potential",
              "effort": 1
            },
            "AKS.Windows": {
              "severity": "potential",
              "effort": 1
            },
            "ACA": {
              "severity": "potential",
              "effort": 1
            },
            "AppServiceContainer.Linux": {
              "severity": "potential",
              "effort": 1
            },
            "AppServiceContainer.Windows": {
              "severity": "potential",
              "effort": 1
            },
            "AppServiceManagedInstance.Windows": {
              "severity": "potential",
              "effort": 1
            }
          },
          "labels": []
        },
        {
          "ruleId": "Local.0006",
          "incidentId": "d6082fca-ab6f-461d-92b6-b5307e6bf900",
          "location": "src\\eShopWinForms\\Connected Services\\eShopServiceReference\\Reference.cs",
          "locationKind": "File",
          "line": 518,
          "column": 63,
          "targets": {
            "AppService.Windows": {
              "severity": "potential",
              "effort": 1
            },
            "AppService.Linux": {
              "severity": "potential",
              "effort": 1
            },
            "AKS.Linux": {
              "severity": "potential",
              "effort": 1
            },
            "AKS.Windows": {
              "severity": "potential",
              "effort": 1
            },
            "ACA": {
              "severity": "potential",
              "effort": 1
            },
            "AppServiceContainer.Linux": {
              "severity": "potential",
              "effort": 1
            },
            "AppServiceContainer.Windows": {
              "severity": "potential",
              "effort": 1
            },
            "AppServiceManagedInstance.Windows": {
              "severity": "potential",
              "effort": 1
            }
          },
          "labels": []
        },
        {
          "ruleId": "Local.0006",
          "incidentId": "1d075044-9577-4283-9ed6-ea6ca721b6dd",
          "location": "src\\eShopWinForms\\Connected Services\\eShopServiceReference\\Reference.cs",
          "locationKind": "File",
          "line": 521,
          "column": 63,
          "targets": {
            "AppService.Windows": {
              "severity": "potential",
              "effort": 1
            },
            "AppService.Linux": {
              "severity": "potential",
              "effort": 1
            },
            "AKS.Linux": {
              "severity": "potential",
              "effort": 1
            },
            "AKS.Windows": {
              "severity": "potential",
              "effort": 1
            },
            "ACA": {
              "severity": "potential",
              "effort": 1
            },
            "AppServiceContainer.Linux": {
              "severity": "potential",
              "effort": 1
            },
            "AppServiceContainer.Windows": {
              "severity": "potential",
              "effort": 1
            },
            "AppServiceManagedInstance.Windows": {
              "severity": "potential",
              "effort": 1
            }
          },
          "labels": []
        },
        {
          "ruleId": "Local.0006",
          "incidentId": "9492d959-69a8-4b57-b6ad-71aa2a42ce1a",
          "location": "src\\eShopWinForms\\Connected Services\\eShopServiceReference\\Reference.cs",
          "locationKind": "File",
          "line": 518,
          "column": 129,
          "targets": {
            "AppService.Windows": {
              "severity": "potential",
              "effort": 1
            },
            "AppService.Linux": {
              "severity": "potential",
              "effort": 1
            },
            "AKS.Linux": {
              "severity": "potential",
              "effort": 1
            },
            "AKS.Windows": {
              "severity": "potential",
              "effort": 1
            },
            "ACA": {
              "severity": "potential",
              "effort": 1
            },
            "AppServiceContainer.Linux": {
              "severity": "potential",
              "effort": 1
            },
            "AppServiceContainer.Windows": {
              "severity": "potential",
              "effort": 1
            },
            "AppServiceManagedInstance.Windows": {
              "severity": "potential",
              "effort": 1
            }
          },
          "labels": []
        },
        {
          "ruleId": "Local.0006",
          "incidentId": "78fd50cb-26f4-4fcc-973c-a3f640e7e498",
          "location": "src\\eShopWinForms\\Connected Services\\eShopServiceReference\\Reference.cs",
          "locationKind": "File",
          "line": 521,
          "column": 129,
          "targets": {
            "AppService.Windows": {
              "severity": "potential",
              "effort": 1
            },
            "AppService.Linux": {
              "severity": "potential",
              "effort": 1
            },
            "AKS.Linux": {
              "severity": "potential",
              "effort": 1
            },
            "AKS.Windows": {
              "severity": "potential",
              "effort": 1
            },
            "ACA": {
              "severity": "potential",
              "effort": 1
            },
            "AppServiceContainer.Linux": {
              "severity": "potential",
              "effort": 1
            },
            "AppServiceContainer.Windows": {
              "severity": "potential",
              "effort": 1
            },
            "AppServiceManagedInstance.Windows": {
              "severity": "potential",
              "effort": 1
            }
          },
          "labels": []
        },
        {
          "ruleId": "Local.0006",
          "incidentId": "af169af9-69d3-4802-a966-49b650366463",
          "location": "src\\eShopWinForms\\Connected Services\\eShopServiceReference\\Reference.cs",
          "locationKind": "File",
          "line": 554,
          "column": 63,
          "targets": {
            "AppService.Windows": {
              "severity": "potential",
              "effort": 1
            },
            "AppService.Linux": {
              "severity": "potential",
              "effort": 1
            },
            "AKS.Linux": {
              "severity": "potential",
              "effort": 1
            },
            "AKS.Windows": {
              "severity": "potential",
              "effort": 1
            },
            "ACA": {
              "severity": "potential",
              "effort": 1
            },
            "AppServiceContainer.Linux": {
              "severity": "potential",
              "effort": 1
            },
            "AppServiceContainer.Windows": {
              "severity": "potential",
              "effort": 1
            },
            "AppServiceManagedInstance.Windows": {
              "severity": "potential",
              "effort": 1
            }
          },
          "labels": []
        },
        {
          "ruleId": "Local.0006",
          "incidentId": "78c7bf8e-5354-437c-96ba-e01b5995326a",
          "location": "src\\eShopWinForms\\Connected Services\\eShopServiceReference\\Reference.cs",
          "locationKind": "File",
          "line": 557,
          "column": 63,
          "targets": {
            "AppService.Windows": {
              "severity": "potential",
              "effort": 1
            },
            "AppService.Linux": {
              "severity": "potential",
              "effort": 1
            },
            "AKS.Linux": {
              "severity": "potential",
              "effort": 1
            },
            "AKS.Windows": {
              "severity": "potential",
              "effort": 1
            },
            "ACA": {
              "severity": "potential",
              "effort": 1
            },
            "AppServiceContainer.Linux": {
              "severity": "potential",
              "effort": 1
            },
            "AppServiceContainer.Windows": {
              "severity": "potential",
              "effort": 1
            },
            "AppServiceManagedInstance.Windows": {
              "severity": "potential",
              "effort": 1
            }
          },
          "labels": []
        },
        {
          "ruleId": "Local.0006",
          "incidentId": "e8c7ff1e-5813-458f-bb06-8340cf6ec596",
          "location": "src\\eShopWinForms\\Connected Services\\eShopServiceReference\\Reference.cs",
          "locationKind": "File",
          "line": 554,
          "column": 125,
          "targets": {
            "AppService.Windows": {
              "severity": "potential",
              "effort": 1
            },
            "AppService.Linux": {
              "severity": "potential",
              "effort": 1
            },
            "AKS.Linux": {
              "severity": "potential",
              "effort": 1
            },
            "AKS.Windows": {
              "severity": "potential",
              "effort": 1
            },
            "ACA": {
              "severity": "potential",
              "effort": 1
            },
            "AppServiceContainer.Linux": {
              "severity": "potential",
              "effort": 1
            },
            "AppServiceContainer.Windows": {
              "severity": "potential",
              "effort": 1
            },
            "AppServiceManagedInstance.Windows": {
              "severity": "potential",
              "effort": 1
            }
          },
          "labels": []
        },
        {
          "ruleId": "Local.0006",
          "incidentId": "9bf0fb8a-257f-4fa1-8aaf-4c238c217b5c",
          "location": "src\\eShopWinForms\\Connected Services\\eShopServiceReference\\Reference.cs",
          "locationKind": "File",
          "line": 557,
          "column": 125,
          "targets": {
            "AppService.Windows": {
              "severity": "potential",
              "effort": 1
            },
            "AppService.Linux": {
              "severity": "potential",
              "effort": 1
            },
            "AKS.Linux": {
              "severity": "potential",
              "effort": 1
            },
            "AKS.Windows": {
              "severity": "potential",
              "effort": 1
            },
            "ACA": {
              "severity": "potential",
              "effort": 1
            },
            "AppServiceContainer.Linux": {
              "severity": "potential",
              "effort": 1
            },
            "AppServiceContainer.Windows": {
              "severity": "potential",
              "effort": 1
            },
            "AppServiceManagedInstance.Windows": {
              "severity": "potential",
              "effort": 1
            }
          },
          "labels": []
        },
        {
          "ruleId": "Local.0006",
          "incidentId": "dcea9fbc-ff74-4258-8228-3b4043e1c7a2",
          "location": "src\\eShopWinForms\\Connected Services\\eShopServiceReference\\Reference.cs",
          "locationKind": "File",
          "line": 548,
          "column": 63,
          "targets": {
            "AppService.Windows": {
              "severity": "potential",
              "effort": 1
            },
            "AppService.Linux": {
              "severity": "potential",
              "effort": 1
            },
            "AKS.Linux": {
              "severity": "potential",
              "effort": 1
            },
            "AKS.Windows": {
              "severity": "potential",
              "effort": 1
            },
            "ACA": {
              "severity": "potential",
              "effort": 1
            },
            "AppServiceContainer.Linux": {
              "severity": "potential",
              "effort": 1
            },
            "AppServiceContainer.Windows": {
              "severity": "potential",
              "effort": 1
            },
            "AppServiceManagedInstance.Windows": {
              "severity": "potential",
              "effort": 1
            }
          },
          "labels": []
        },
        {
          "ruleId": "Local.0006",
          "incidentId": "af0e5439-e905-4aee-aff5-dfaa40ac4208",
          "location": "src\\eShopWinForms\\Connected Services\\eShopServiceReference\\Reference.cs",
          "locationKind": "File",
          "line": 551,
          "column": 63,
          "targets": {
            "AppService.Windows": {
              "severity": "potential",
              "effort": 1
            },
            "AppService.Linux": {
              "severity": "potential",
              "effort": 1
            },
            "AKS.Linux": {
              "severity": "potential",
              "effort": 1
            },
            "AKS.Windows": {
              "severity": "potential",
              "effort": 1
            },
            "ACA": {
              "severity": "potential",
              "effort": 1
            },
            "AppServiceContainer.Linux": {
              "severity": "potential",
              "effort": 1
            },
            "AppServiceContainer.Windows": {
              "severity": "potential",
              "effort": 1
            },
            "AppServiceManagedInstance.Windows": {
              "severity": "potential",
              "effort": 1
            }
          },
          "labels": []
        },
        {
          "ruleId": "Local.0006",
          "incidentId": "aa9ab6ab-8b96-482e-b003-acb21a181bbc",
          "location": "src\\eShopWinForms\\Connected Services\\eShopServiceReference\\Reference.cs",
          "locationKind": "File",
          "line": 548,
          "column": 131,
          "targets": {
            "AppService.Windows": {
              "severity": "potential",
              "effort": 1
            },
            "AppService.Linux": {
              "severity": "potential",
              "effort": 1
            },
            "AKS.Linux": {
              "severity": "potential",
              "effort": 1
            },
            "AKS.Windows": {
              "severity": "potential",
              "effort": 1
            },
            "ACA": {
              "severity": "potential",
              "effort": 1
            },
            "AppServiceContainer.Linux": {
              "severity": "potential",
              "effort": 1
            },
            "AppServiceContainer.Windows": {
              "severity": "potential",
              "effort": 1
            },
            "AppServiceManagedInstance.Windows": {
              "severity": "potential",
              "effort": 1
            }
          },
          "labels": []
        },
        {
          "ruleId": "Local.0006",
          "incidentId": "1b277a6e-e81c-4116-aa0e-cac95f5eb73c",
          "location": "src\\eShopWinForms\\Connected Services\\eShopServiceReference\\Reference.cs",
          "locationKind": "File",
          "line": 551,
          "column": 131,
          "targets": {
            "AppService.Windows": {
              "severity": "potential",
              "effort": 1
            },
            "AppService.Linux": {
              "severity": "potential",
              "effort": 1
            },
            "AKS.Linux": {
              "severity": "potential",
              "effort": 1
            },
            "AKS.Windows": {
              "severity": "potential",
              "effort": 1
            },
            "ACA": {
              "severity": "potential",
              "effort": 1
            },
            "AppServiceContainer.Linux": {
              "severity": "potential",
              "effort": 1
            },
            "AppServiceContainer.Windows": {
              "severity": "potential",
              "effort": 1
            },
            "AppServiceManagedInstance.Windows": {
              "severity": "potential",
              "effort": 1
            }
          },
          "labels": []
        },
        {
          "ruleId": "Local.0006",
          "incidentId": "67b2367b-cb83-4675-b3cc-c1de758d0179",
          "location": "src\\eShopWinForms\\Connected Services\\eShopServiceReference\\Reference.cs",
          "locationKind": "File",
          "line": 542,
          "column": 63,
          "targets": {
            "AppService.Windows": {
              "severity": "potential",
              "effort": 1
            },
            "AppService.Linux": {
              "severity": "potential",
              "effort": 1
            },
            "AKS.Linux": {
              "severity": "potential",
              "effort": 1
            },
            "AKS.Windows": {
              "severity": "potential",
              "effort": 1
            },
            "ACA": {
              "severity": "potential",
              "effort": 1
            },
            "AppServiceContainer.Linux": {
              "severity": "potential",
              "effort": 1
            },
            "AppServiceContainer.Windows": {
              "severity": "potential",
              "effort": 1
            },
            "AppServiceManagedInstance.Windows": {
              "severity": "potential",
              "effort": 1
            }
          },
          "labels": []
        },
        {
          "ruleId": "Local.0006",
          "incidentId": "7094018c-afe1-4d1b-8998-ce6575a5065f",
          "location": "src\\eShopWinForms\\Connected Services\\eShopServiceReference\\Reference.cs",
          "locationKind": "File",
          "line": 545,
          "column": 63,
          "targets": {
            "AppService.Windows": {
              "severity": "potential",
              "effort": 1
            },
            "AppService.Linux": {
              "severity": "potential",
              "effort": 1
            },
            "AKS.Linux": {
              "severity": "potential",
              "effort": 1
            },
            "AKS.Windows": {
              "severity": "potential",
              "effort": 1
            },
            "ACA": {
              "severity": "potential",
              "effort": 1
            },
            "AppServiceContainer.Linux": {
              "severity": "potential",
              "effort": 1
            },
            "AppServiceContainer.Windows": {
              "severity": "potential",
              "effort": 1
            },
            "AppServiceManagedInstance.Windows": {
              "severity": "potential",
              "effort": 1
            }
          },
          "labels": []
        },
        {
          "ruleId": "Local.0006",
          "incidentId": "96329928-e3d3-4c91-a9d5-af28a5102744",
          "location": "src\\eShopWinForms\\Connected Services\\eShopServiceReference\\Reference.cs",
          "locationKind": "File",
          "line": 542,
          "column": 131,
          "targets": {
            "AppService.Windows": {
              "severity": "potential",
              "effort": 1
            },
            "AppService.Linux": {
              "severity": "potential",
              "effort": 1
            },
            "AKS.Linux": {
              "severity": "potential",
              "effort": 1
            },
            "AKS.Windows": {
              "severity": "potential",
              "effort": 1
            },
            "ACA": {
              "severity": "potential",
              "effort": 1
            },
            "AppServiceContainer.Linux": {
              "severity": "potential",
              "effort": 1
            },
            "AppServiceContainer.Windows": {
              "severity": "potential",
              "effort": 1
            },
            "AppServiceManagedInstance.Windows": {
              "severity": "potential",
              "effort": 1
            }
          },
          "labels": []
        },
        {
          "ruleId": "Local.0006",
          "incidentId": "0eb3500e-12a2-4f5e-89b6-6958e0151e81",
          "location": "src\\eShopWinForms\\Connected Services\\eShopServiceReference\\Reference.cs",
          "locationKind": "File",
          "line": 545,
          "column": 131,
          "targets": {
            "AppService.Windows": {
              "severity": "potential",
              "effort": 1
            },
            "AppService.Linux": {
              "severity": "potential",
              "effort": 1
            },
            "AKS.Linux": {
              "severity": "potential",
              "effort": 1
            },
            "AKS.Windows": {
              "severity": "potential",
              "effort": 1
            },
            "ACA": {
              "severity": "potential",
              "effort": 1
            },
            "AppServiceContainer.Linux": {
              "severity": "potential",
              "effort": 1
            },
            "AppServiceContainer.Windows": {
              "severity": "potential",
              "effort": 1
            },
            "AppServiceManagedInstance.Windows": {
              "severity": "potential",
              "effort": 1
            }
          },
          "labels": []
        }
      ]
    }
  ],
  "rules": {
    "Runtime.0002": {
      "id": "Runtime.0002",
      "description": "Upgrade to newer target framework to get better cloud experience.\n\nIf you are targeting Managed Instance on Azure App Service, validate on .NET Framework 4.8 or move to .NET 10. Persist any runtime prerequisites via install scripts; test in staging before production.\n\nWhile if targeting other Azure compute services:\n\nApplication targeting .NET framework lower than 4.7.1 might missing features that would be needed for some cloud scenarios like scaling or getting secrets from secure external sources.\n\nAzure App Service runs apps on .NET Framework 4.8 or .NET Framework 3.5. Apps running on on .NET Framework versions older than .NET Framework 4.8 could have potential compatibility issues. It is recommended to test your application running on .NET Framework 4.8. Note that it is not necessary to re-target to .NET Framework 4.8, only to validate that the app correctly runs on that version of .NET Framework.\n\nIn the long term it is also recommended to upgrade your application to latest supported .NET 8\u002B which would significantly increase performance of your application. Use tools like .NET Upgrade Assistant to help with upgrading your application to newer .NET.",
      "title": "Upgrade to newer target framework to get better cloud experience",
      "severity": "optional",
      "effort": 3,
      "links": [
        {
          "title": "[Managed Instance] Install scripts",
          "url": "https://go.microsoft.com/fwlink/?linkid=2347059"
        },
        {
          "title": ".NET Framework Breaking Changes",
          "url": "https://go.microsoft.com/fwlink/?linkid=2250029"
        },
        {
          "title": ".NET Framework 4.8 on App Service",
          "url": "https://go.microsoft.com/fwlink/?linkid=2251730"
        },
        {
          "title": "Upgrade to latest .NET with Upgrade Assistant",
          "url": "https://go.microsoft.com/fwlink/?LinkID=2202641"
        }
      ],
      "labels": []
    },
    "Database.0002": {
      "id": "Database.0002",
      "description": "SQL database connection detected.\n\nEnsure the database is available/reachable on Azure.\n\nIf it is not, there are multiple ways you can move your data to Azure:\n    1. Migrate to Azure SQL Database.\n    2. Consider Azure SQL Managed Instance if you need features that are not available in Azure SQL Database and you don\u2019t want to use a VM.\n    3. Migrate your database servers directly to SQL Server on Azure VMs.\n\nTo assess database migration effort, you can use Azure Migrate tool, see the link below.",
      "title": "SQL database connection detected",
      "severity": "potential",
      "effort": 3,
      "links": [
        {
          "title": "Migrate SQL Server database to Azure",
          "url": "https://go.microsoft.com/fwlink/?LinkID=2251731"
        },
        {
          "title": "Azure SQL Managed Instance",
          "url": "https://go.microsoft.com/fwlink/?LinkID=2251613"
        },
        {
          "title": "Azure Migrate",
          "url": "https://go.microsoft.com/fwlink/?linkid=2252410"
        }
      ],
      "labels": []
    },
    "Database.0003": {
      "id": "Database.0003",
      "description": "System.Data.SqlClient dependency is detected.\n\nWhile System.Data.SqlClient will work in Azure, the newer Microsoft.Data.SqlClient package is the primary .NET SQL client moving forward and receiving the latest features. For example, Microsoft.Data.SqlClient easily allows use of Azure Managed Identity from a connection string.",
      "title": "System.Data.SqlClient dependency detected",
      "severity": "optional",
      "effort": 3,
      "links": [
        {
          "url": "https://go.microsoft.com/fwlink/?LinkID=2242668"
        }
      ],
      "labels": []
    },
    "Security.0002": {
      "id": "Security.0002",
      "description": "Connection strings without configuration builders detected.  \n\n Keeping connection strings directly in the app is not the best practice and might introduce security risks, increased maintenance, scalability challenges or compliance standards (such as PCI DSS, GDPR, etc.). \n\n Instead, it is recommended to use configuration builders to get secrets from secure sources in Azure environment.",
      "title": "Connection strings without configuration builders detected",
      "severity": "optional",
      "effort": 3,
      "links": [
        {
          "title": "Configuration builders",
          "url": "https://go.microsoft.com/fwlink/?LinkID=2250915"
        },
        {
          "title": "Storing application secrets",
          "url": "https://go.microsoft.com/fwlink/?LinkID=2250916"
        },
        {
          "title": "Centralized app configuration and security",
          "url": "https://go.microsoft.com/fwlink/?LinkID=2250733"
        }
      ],
      "labels": []
    },
    "Scale.0001": {
      "id": "Scale.0001",
      "description": "Static content detected.\n\nYour current approach of serving static content directly might lead to increased costs, performance issues, maintenance challenges (requiring application redeployment for content changes), and security risks.\n\nConsider moving static content to Azure Blob Storage and adding Azure CDN.",
      "title": "Static content detected",
      "severity": "optional",
      "effort": 3,
      "links": [
        {
          "title": "Azure Blob Storage",
          "url": "https://go.microsoft.com/fwlink/?linkid=2250574"
        },
        {
          "title": "Azure CDN",
          "url": "https://go.microsoft.com/fwlink/?linkid=2250392"
        }
      ],
      "labels": []
    },
    "Local.0003": {
      "id": "Local.0003",
      "description": "Your application has local or network IO operations.\n\nIf you are targeting Managed Instance on Azure App Service, move persistent I/O to storage mounts (Azure Files/UNC). Keep local writes to temp only; connect to external dependencies via private endpoints/VNet to reduce latency.\n\nIO operations outside of the application folder might not be available on Azure App Service. Review and ensure IO APIs are attempting to access paths that will be available when your app is running on App Service sandbox. If you choose the containerized hosting option, your scenario still might be broken or have scalability issues.\n\nPossible solutions:\n    1. Files that the application needs can be deployed with the application or put in Azure Storage. You can use Azure Storage File Shares as a drop-in replacement for on-premises file share.\n    2. Other services that the application depends on might need to be migrated to Azure, this way you will get the benefit of lower latency in the cloud.\n    3. If your application needs to depend on services that run on-premise, you can connect your Azure and local networks with ExpressRoute, Hybrid Connections, or VPN solutions.",
      "title": "Local or network IO operations detected",
      "severity": "potential",
      "effort": 3,
      "links": [
        {
          "title": "[Managed Instance] Storage mounts",
          "url": "https://go.microsoft.com/fwlink/?linkid=2346952"
        },
        {
          "title": "Azure file share",
          "url": "https://go.microsoft.com/fwlink/?LinkID=2242591"
        },
        {
          "title": "ExpressRoute",
          "url": "https://go.microsoft.com/fwlink/?LinkID=2250577"
        },
        {
          "title": "Hybrid Connections",
          "url": "https://go.microsoft.com/fwlink/?LinkID=2242588"
        },
        {
          "title": "Connect an on-prem network",
          "url": "https://go.microsoft.com/fwlink/?LinkID=2242591"
        },
        {
          "title": "Design to scale out",
          "url": "https://go.microsoft.com/fwlink/?linkid=2251007"
        }
      ],
      "labels": []
    },
    "Local.0007": {
      "id": "Local.0007",
      "description": "Local OS environment access detected.\n\nIf you are targeting Managed Instance on Azure App Service, Read config via App Settings or App Configuration; avoid machine\u2011specific environment APIs. Persist environment setup via install scripts when needed.\n\nWhen running in Azure App Service environment, your application can read environment variables that you define in App Service settings. Using environment API other than reading environment variables might indicate that your application depends on some local machine\u0027s features and might be broken on App Service sandbox or not scale well. Review your scenarios and either refactor them to be more cloud friendly or choose the option in App Service to host your application in the sandbox for Windows Container Web Apps.\n\nIf you choose to use other Azure hosting options such as Azure Container Apps (ACA) or Azure Kubernetes Service (AKS), environment APIs might work, however scaling still might be an issue.",
      "title": "Local OS environment access detected",
      "severity": "potential",
      "effort": 1,
      "links": [
        {
          "title": "General App Service sandbox restrictions",
          "url": "https://go.microsoft.com/fwlink/?linkid=2250496"
        },
        {
          "title": "App Service sandbox for Windows Container Web Apps",
          "url": "https://go.microsoft.com/fwlink/?linkid=2251963"
        },
        {
          "title": "Design to scale out",
          "url": "https://go.microsoft.com/fwlink/?linkid=2251007"
        }
      ],
      "labels": []
    },
    "Local.0006": {
      "id": "Local.0006",
      "description": "Your application has hardcoded URLs that might correspond to services that are not accessible on Azure.\n\nReview and ensure that the application is attempting to access URLs that would be available from Azure. You might need to migrate those services to Azure too, this way you will get the benefit of lower latency in the cloud.\n\nIf your application needs to depend on services that run on-premises, you can connect your Azure and local networks with ExpressRoute, Hybrid Connections, or VPN solutions.",
      "title": "Hardcoded URLs detected",
      "severity": "potential",
      "effort": 1,
      "links": [
        {
          "title": "ExpressRoute",
          "url": "https://go.microsoft.com/fwlink/?LinkID=2250577"
        },
        {
          "title": "Hybrid Connections",
          "url": "https://go.microsoft.com/fwlink/?LinkID=2242588"
        },
        {
          "title": "Connect an on-prem network",
          "url": "https://go.microsoft.com/fwlink/?LinkID=2242591"
        }
      ],
      "labels": []
    }
  }
}